glimcrawl/__init__.py
glimcrawl/_version.py
glimcrawl/cli.py
glimcrawl/google_image.py
glimcrawl/image_downloader.py
glimcrawl/image_processor.py
glimcrawl-0.1.2.dist-info/METADATA
glimcrawl-0.1.2.dist-info/WHEEL
glimcrawl-0.1.2.dist-info/entry_points.txt
glimcrawl-0.1.2.dist-info/licenses/LICENSE
glimcrawl-0.1.2.dist-info/RECORD
