Metadata-Version: 2.4
Name: glimcrawl
Version: 0.1.2
Summary: A powerful Google image crawler that supports batch downloading, image processing, and proxy settings
Project-URL: Homepage, https://gitee.com/duckweeds7/glimcrawl
Project-URL: Repository, https://gitee.com/duckweeds7/glimcrawl
Project-URL: Documentation, https://gitee.com/duckweeds7/glimcrawl#readme
Project-URL: Issues, https://gitee.com/duckweeds7/glimcrawl/issues
Project-URL: Changelog, https://gitee.com/duckweeds7/glimcrawl/blob/master/CHANGELOG.md
Author-email: Duckweeds7 <root@duckweeds7.com>
License: MIT
License-File: LICENSE
Keywords: crawler,download,google,image,process
Classifier: Development Status :: 4 - Beta
Classifier: Intended Audience :: Developers
Classifier: License :: OSI Approved :: MIT License
Classifier: Programming Language :: Python :: 3
Classifier: Programming Language :: Python :: 3.8
Classifier: Programming Language :: Python :: 3.9
Classifier: Programming Language :: Python :: 3.10
Classifier: Programming Language :: Python :: 3.11
Classifier: Topic :: Software Development :: Libraries :: Python Modules
Requires-Python: >=3.8
Requires-Dist: aiohttp>=3.9.1
Requires-Dist: loguru>=0.7.2
Requires-Dist: pillow>=10.0.0
Requires-Dist: playwright>=1.41.2
Requires-Dist: rich>=13.7.0
Requires-Dist: typer>=0.9.0
